README.md
setup.py
F19NB/__init__.py
F19NB.egg-info/PKG-INFO
F19NB.egg-info/SOURCES.txt
F19NB.egg-info/dependency_links.txt
F19NB.egg-info/requires.txt
F19NB.egg-info/top_level.txt