Metadata-Version: 2.1
Name: F19NB
Version: 1.0.3
Summary: Tools for the F19NB class at Heriot-Watt University
Home-page: https://github.com/sloisel/pyptex
Author: Sébastien Loisel
License: BSD
Platform: UNKNOWN
